linuxcmd/__init__.py
linuxcmd-1.1.3.dist-info/DESCRIPTION.rst
linuxcmd-1.1.3.dist-info/METADATA
linuxcmd-1.1.3.dist-info/RECORD
linuxcmd-1.1.3.dist-info/WHEEL
linuxcmd-1.1.3.dist-info/metadata.json
linuxcmd-1.1.3.dist-info/top_level.txt
