Metadata-Version: 2.0
Name: linuxcmd
Version: 1.1.3
Summary: A simple tool which extends useful linux based scripting functionalities.
Home-page: https://github.com/Adityank003/linuxcmd
Author: Aditya nk
Author-email: adityank003@gmail.com
License: UNKNOWN
Platform: UNKNOWN
Classifier: Programming Language :: Python :: 2
Classifier: License :: OSI Approved :: MIT License
Classifier: Operating System :: OS Independent
